jupyterlab_jhub_apps/__init__.py
jupyterlab_jhub_apps/_version.py
jupyterlab_jhub_apps-0.3.1.data/data/share/jupyter/labextensions/jupyterlab-jhub-apps/package.json
jupyterlab_jhub_apps-0.3.1.data/data/share/jupyter/labextensions/jupyterlab-jhub-apps/schemas/jupyterlab-jhub-apps/commands.json
jupyterlab_jhub_apps-0.3.1.data/data/share/jupyter/labextensions/jupyterlab-jhub-apps/schemas/jupyterlab-jhub-apps/package.json.orig
jupyterlab_jhub_apps-0.3.1.data/data/share/jupyter/labextensions/jupyterlab-jhub-apps/static/628.6b0e426a7757a25980d3.js
jupyterlab_jhub_apps-0.3.1.data/data/share/jupyter/labextensions/jupyterlab-jhub-apps/static/728.16f310623971c56f3538.js
jupyterlab_jhub_apps-0.3.1.data/data/share/jupyter/labextensions/jupyterlab-jhub-apps/static/remoteEntry.cdaf297ce43fa75ea69f.js
jupyterlab_jhub_apps-0.3.1.data/data/share/jupyter/labextensions/jupyterlab-jhub-apps/static/style.js
jupyterlab_jhub_apps-0.3.1.data/data/share/jupyter/labextensions/jupyterlab-jhub-apps/static/third-party-licenses.json
jupyterlab_jhub_apps-0.3.1.data/data/share/jupyter/labextensions/jupyterlab-jhub-apps/install.json
jupyterlab_jhub_apps-0.3.1.dist-info/METADATA
jupyterlab_jhub_apps-0.3.1.dist-info/WHEEL
jupyterlab_jhub_apps-0.3.1.dist-info/licenses/LICENSE
jupyterlab_jhub_apps-0.3.1.dist-info/RECORD
