Metadata-Version: 2.3
Name: jupyterlab_jhub_apps
Version: 0.3.1
Summary: Customizations for jhub-apps.
Project-URL: Homepage, https://github.com/nebari-dev/jupyterlab-jhub-apps
Project-URL: Bug Tracker, https://github.com/nebari-dev/jupyterlab-jhub-apps/issues
Project-URL: Repository, https://github.com/nebari-dev/jupyterlab-jhub-apps.git
Author-email: Nick Byrne <nbyrne@quansight.com>
License: BSD 3-Clause License
License-File: LICENSE
Keywords: jupyter,jupyterlab,jupyterlab-extension
Classifier: Framework :: Jupyter
Classifier: Framework :: Jupyter :: JupyterLab
Classifier: Framework :: Jupyter :: JupyterLab :: 4
Classifier: Framework :: Jupyter :: JupyterLab :: Extensions
Classifier: Framework :: Jupyter :: JupyterLab :: Extensions :: Prebuilt
Classifier: License :: OSI Approved :: BSD License
Classifier: Programming Language :: Python
Classifier: Programming Language :: Python :: 3
Classifier: Programming Language :: Python :: 3.8
Classifier: Programming Language :: Python :: 3.9
Classifier: Programming Language :: Python :: 3.10
Classifier: Programming Language :: Python :: 3.11
Classifier: Programming Language :: Python :: 3.12
Requires-Python: >=3.8
